{
  "level": "3", 
  "questions": [
    {
      "distractor": {
        "nonsensical": null, 
        "plausible": null, 
        "ungrammatical": [
          "za", 
          "wakati", 
          "wake"
        ], 
        "ungrammatical_english": [
          "of", 
          "time", 
          "his"
        ]
      }, 
      "punctuation": ".", 
      "sentence": "Hapo kale palikuwa na mtu aliyeishi na mkewe aliyempenda sana.", 
      "stem": "Hapo kale palikuwa na mtu aliyeishi na mkewe aliyempenda", 
      "target": "sana"
    }, 
    {
      "distractor": {
        "nonsensical": [
          "elimu", 
          "kucha", 
          "mkutano"
        ], 
        "nonsensical_english": [
          "education", 
          "warbler", 
          "meeting"
        ], 
        "plausible": [
          "makao", 
          "manyatta", 
          "mashine"
        ], 
        "plausible_english": [
          "residence", 
          "homestead", 
          "machine"
        ], 
        "ungrammatical": [
          "dogo", 
          "mashimo", 
          "yu"
        ], 
        "ungrammatical_english": [
          "small", 
          "holes", 
          "he"
        ]
      }, 
      "punctuation": ".", 
      "sentence": "Siku moja alikwenda msituni kwa matembezi.", 
      "stem": "Siku moja alikwenda msituni kwa", 
      "target": "matembezi"
    }, 
    {
      "distractor": {
        "nonsensical": [
          "bado", 
          "bila", 
          "njiani"
        ], 
        "nonsensical_english": [
          "not ready", 
          "without", 
          "along"
        ], 
        "plausible": null, 
        "ungrammatical": [
          "baridi", 
          "majani", 
          "ndugu"
        ], 
        "ungrammatical_english": [
          "chill", 
          "green", 
          "fellow"
        ]
      }, 
      "punctuation": ".", 
      "sentence": "Njiani alikutana na msichana mmoja mwembamba na mrembo mno.", 
      "stem": "Njiani alikutana na msichana mmoja mwembamba na mrembo", 
      "target": "mno"
    }, 
    {
      "distractor": {
        "nonsensical": [
          "kwanza", 
          "kila", 
          "kidogo"
        ], 
        "nonsensical_english": [
          "first", 
          "daily", 
          "little"
        ], 
        "plausible": [
          "kila", 
          "mbali", 
          "kidogo"
        ], 
        "plausible_english": [
          "each", 
          "entirely", 
          "few"
        ], 
        "ungrammatical": [
          "mti", 
          "chakula", 
          "kwamba"
        ], 
        "ungrammatical_english": [
          "fruit-tree", 
          "dinner", 
          "order"
        ]
      }, 
      "punctuation": ".", 
      "sentence": "Alimpenda papo hapo.", 
      "stem": "Alimpenda papo", 
      "target": "hapo"
    }, 
    {
      "distractor": {
        "nonsensical": null, 
        "plausible": null, 
        "ungrammatical": [
          "la", 
          "cha", 
          "kwamba"
        ], 
        "ungrammatical_english": [
          "it", 
          "light", 
          "that"
        ]
      }, 
      "punctuation": ".", 
      "sentence": "Msichana vile vile alimkubali mara moja.", 
      "stem": "Msichana vile vile alimkubali mara", 
      "target": "moja"
    }, 
    {
      "distractor": {
        "nonsensical": null, 
        "plausible": null, 
        "ungrammatical": [
          "upepo", 
          "mtoto", 
          "ndovu"
        ], 
        "ungrammatical_english": [
          "change", 
          "infant", 
          "elephant"
        ]
      }, 
      "punctuation": ".", 
      "sentence": "Lakini, msichana alimwambia kuwa alikuwa na titi moja tu.", 
      "stem": "Lakini, msichana alimwambia kuwa alikuwa na titi moja", 
      "target": "tu"
    }, 
    {
      "distractor": null, 
      "punctuation": ".", 
      "sentence": "Kwa hivyo alimwambia aende nyumbani, akate titi moja la mkewe amletee.", 
      "stem": "Kwa hivyo alimwambia aende nyumbani, akate titi moja la mkewe", 
      "target": "amletee"
    }, 
    {
      "distractor": null, 
      "punctuation": ".", 
      "sentence": "Kwa njia hii angekuwa na matiti mawili hivyo wangeoana.", 
      "stem": "Kwa njia hii angekuwa na matiti mawili hivyo", 
      "target": "wangeoana"
    }, 
    {
      "distractor": {
        "nonsensical": null, 
        "plausible": null, 
        "ungrammatical": [
          "sana", 
          "kisha", 
          "wakati"
        ], 
        "ungrammatical_english": [
          "most", 
          "if", 
          "whenever"
        ]
      }, 
      "punctuation": ".", 
      "sentence": "Mwanamme alikimbia kwa kasi, akachukuwa kisu, akamrukia mkewe mpendwa na kukata titi lake mara moja.", 
      "stem": "Mwanamme alikimbia kwa kasi, akachukuwa kisu, akamrukia mkewe mpendwa na kukata titi lake mara", 
      "target": "moja"
    }, 
    {
      "distractor": null, 
      "punctuation": ".", 
      "sentence": "Aliharakisha kwenda msituni alikomwacha mpenzi wake mpya.", 
      "stem": "Aliharakisha kwenda msituni alikomwacha mpenzi wake", 
      "target": "mpya"
    }, 
    {
      "distractor": null, 
      "punctuation": ".", 
      "sentence": "Lakini hakuwapo.", 
      "stem": "Lakini", 
      "target": "hakuwapo"
    }, 
    {
      "distractor": {
        "nonsensical": null, 
        "plausible": null, 
        "ungrammatical": [
          "chungu", 
          "hao", 
          "hadithi"
        ], 
        "ungrammatical_english": [
          "acrid", 
          "those", 
          "describe"
        ]
      }, 
      "punctuation": ".", 
      "sentence": "Aliliita jina lake kwa sauti, lakini ilikuwa kimya tu.", 
      "stem": "Aliliita jina lake kwa sauti, lakini ilikuwa kimya", 
      "target": "tu"
    }, 
    {
      "distractor": null, 
      "punctuation": "?", 
      "sentence": "Kisha alisikia sauti ikisema, \"Kwa nini unaita?", 
      "stem": "Kisha alisikia sauti ikisema, \"Kwa nini", 
      "target": "unaita"
    }, 
    {
      "distractor": null, 
      "punctuation": "?\"", 
      "sentence": "Kwani hujui kwamba uko katika msitu wa Musambwa kwa Libeeletwela?\"", 
      "stem": "Kwani hujui kwamba uko katika msitu wa Musambwa kwa", 
      "target": "Libeeletwela"
    }, 
    {
      "distractor": {
        "nonsensical": [
          "ua", 
          "panda", 
          "hifadhi"
        ], 
        "nonsensical_english": [
          "courtyard", 
          "sling", 
          "save"
        ], 
        "plausible": [
          "zama", 
          "afya", 
          "panga"
        ], 
        "plausible_english": [
          "epoch", 
          "health", 
          "prickly"
        ], 
        "ungrammatical": [
          "ambavyo", 
          "ovyo", 
          "maarufu"
        ], 
        "ungrammatical_english": [
          "that", 
          "excessively", 
          "esteemed"
        ]
      }, 
      "punctuation": "...", 
      "sentence": "Mtu yule aliposikia hivyo, alikimbia nyumbani kwa kasi kama risasi...", 
      "stem": "Mtu yule aliposikia hivyo, alikimbia nyumbani kwa kasi kama", 
      "target": "risasi"
    }, 
    {
      "distractor": null, 
      "punctuation": ".", 
      "sentence": "Alimpata mkewe tayari akiwa amefariki.", 
      "stem": "Alimpata mkewe tayari akiwa", 
      "target": "amefariki"
    }, 
    {
      "distractor": null, 
      "punctuation": ".", 
      "sentence": "Alihuzunika sana kwa ajili ya yale alikuwa amefanya.", 
      "stem": "Alihuzunika sana kwa ajili ya yale alikuwa", 
      "target": "amefanya"
    }, 
    {
      "distractor": {
        "nonsensical": [
          "kitendo", 
          "ujuzi", 
          "umbo"
        ], 
        "nonsensical_english": [
          "practices", 
          "expertise", 
          "appearance"
        ], 
        "plausible": [
          "kucha", 
          "kuuliza", 
          "kukata"
        ], 
        "plausible_english": [
          "warbler", 
          "question", 
          "shortcut"
        ], 
        "ungrammatical": [
          "ina", 
          "tuli", 
          "tazama"
        ], 
        "ungrammatical_english": [
          "certainly", 
          "still", 
          "test"
        ]
      }, 
      "punctuation": ".", 
      "sentence": "Naye alitaka kufa.", 
      "stem": "Naye alitaka", 
      "target": "kufa"
    }
  ], 
  "title": "placeholder"
}