{
  "authors": "Mozambican folktale",
  "copyright": "Copyright (c) Mozambican folktale, 2014",
  "data": [
    {
      "image": "level2_14_page_02_image_0001.jpg",
      "text": [
        [
          {
            "narration": [
              {
                "audio": "hapo_zamani_za_kale_palikuwa_na_mtu_aliyekuwa_akitembea_kichakani.mp3",
                "from": 19,
                "segmentation": [
                  {
                    "end": 65,
                    "start": 19,
                    "word": "Hapo"
                  },
                  {
                    "end": 127,
                    "start": 66,
                    "word": "zamani"
                  },
                  {
                    "end": 150,
                    "start": 128,
                    "word": "za"
                  },
                  {
                    "end": 201,
                    "start": 151,
                    "word": "kale"
                  },
                  {
                    "end": 334,
                    "start": 262,
                    "word": "palikuwa"
                  },
                  {
                    "end": 356,
                    "start": 335,
                    "word": "na"
                  },
                  {
                    "end": 405,
                    "start": 357,
                    "word": "mtu"
                  },
                  {
                    "end": 506,
                    "start": 421,
                    "word": "aliyekuwa"
                  },
                  {
                    "end": 609,
                    "start": 519,
                    "word": "akitembea"
                  },
                  {
                    "end": 710,
                    "start": 610,
                    "word": "kichakani"
                  }
                ],
                "until": 710,
                "utterances": "Hapo zamani za kale palikuwa na mtu aliyekuwa akitembea kichakani"
              }
            ],
            "sentence": "Hapo zamani za kale, palikuwa na mtu aliyekuwa akitembea kichakani."
          }
        ],
        [
          {
            "narration": [
              {
                "audio": "ghafla_alikutana_na_simba.mp3",
                "from": 24,
                "segmentation": [
                  {
                    "end": 77,
                    "start": 24,
                    "word": "Ghafla"
                  },
                  {
                    "end": 203,
                    "start": 78,
                    "word": "alikutana"
                  },
                  {
                    "end": 222,
                    "start": 204,
                    "word": "na"
                  },
                  {
                    "end": 278,
                    "start": 223,
                    "word": "Simba"
                  }
                ],
                "until": 278,
                "utterances": "Ghafla alikutana na Simba"
              }
            ],
            "sentence": "Ghafla, alikutana na Simba!"
          }
        ]
      ]
    },
    {
      "image": "level2_14_page_03_image_0001.jpg",
      "text": [
        [
          {
            "narration": [
              {
                "audio": "simba_alikuwa_akipumzika_katika_nyasi_fupi_za_msimu_wa_baridi.mp3",
                "from": 58,
                "segmentation": [
                  {
                    "end": 121,
                    "start": 58,
                    "word": "Simba"
                  },
                  {
                    "end": 189,
                    "start": 125,
                    "word": "alikuwa"
                  },
                  {
                    "end": 334,
                    "start": 190,
                    "word": "akipumzika"
                  },
                  {
                    "end": 388,
                    "start": 335,
                    "word": "katika"
                  },
                  {
                    "end": 433,
                    "start": 389,
                    "word": "nyasi"
                  },
                  {
                    "end": 500,
                    "start": 434,
                    "word": "fupi"
                  },
                  {
                    "end": 551,
                    "start": 533,
                    "word": "za"
                  },
                  {
                    "end": 622,
                    "start": 552,
                    "word": "msimu"
                  },
                  {
                    "end": 633,
                    "start": 623,
                    "word": "wa"
                  },
                  {
                    "end": 708,
                    "start": 634,
                    "word": "baridi"
                  }
                ],
                "until": 708,
                "utterances": "Simba alikuwa akipumzika katika nyasi fupi za msimu wa baridi"
              }
            ],
            "sentence": "Simba alikuwa akipumzika katika nyasi fupi za msimu wa baridi."
          }
        ]
      ]
    },
    {
      "image": "level2_14_page_04_image_0001.jpg",
      "text": [
        [
          {
            "narration": [
              {
                "audio": "makutano_hayo_yalitokea_ghafla_mtu_huyo_asijue_la_kufanya.mp3",
                "from": 21,
                "segmentation": [
                  {
                    "end": 114,
                    "start": 21,
                    "word": "Makutano"
                  },
                  {
                    "end": 178,
                    "start": 115,
                    "word": "hayo"
                  },
                  {
                    "end": 286,
                    "start": 179,
                    "word": "yalitokea"
                  },
                  {
                    "end": 349,
                    "start": 287,
                    "word": "ghafla"
                  },
                  {
                    "end": 431,
                    "start": 398,
                    "word": "mtu"
                  },
                  {
                    "end": 482,
                    "start": 432,
                    "word": "huyo"
                  },
                  {
                    "end": 541,
                    "start": 483,
                    "word": "asijue"
                  },
                  {
                    "end": 557,
                    "start": 542,
                    "word": "la"
                  },
                  {
                    "end": 623,
                    "start": 558,
                    "word": "kufanya"
                  }
                ],
                "until": 623,
                "utterances": "Makutano hayo yalitokea ghafla mtu huyo asijue la kufanya"
              }
            ],
            "sentence": "Makutano hayo yalitokea ghafla mtu huyo asijue la kufanya."
          }
        ],
        [
          {
            "narration": [
              {
                "audio": "alijawa_na_woga.mp3",
                "from": 22,
                "segmentation": [
                  {
                    "end": 130,
                    "start": 22,
                    "word": "Alijawa"
                  },
                  {
                    "end": 155,
                    "start": 131,
                    "word": "na"
                  },
                  {
                    "end": 225,
                    "start": 156,
                    "word": "woga"
                  }
                ],
                "until": 225,
                "utterances": "Alijawa na woga"
              }
            ],
            "sentence": "Alijawa na woga."
          }
        ]
      ]
    },
    {
      "image": "level2_14_page_05_image_0001.jpg",
      "text": [
        [
          {
            "narration": [
              {
                "audio": "mwanzoni_simba_alishangaa_pia_na_kuogopa_kidogo.mp3",
                "from": 28,
                "segmentation": [
                  {
                    "end": 132,
                    "start": 28,
                    "word": "Mwanzoni"
                  },
                  {
                    "end": 211,
                    "start": 161,
                    "word": "Simba"
                  },
                  {
                    "end": 349,
                    "start": 212,
                    "word": "alishangaa"
                  },
                  {
                    "end": 443,
                    "start": 407,
                    "word": "pia"
                  },
                  {
                    "end": 498,
                    "start": 486,
                    "word": "na"
                  },
                  {
                    "end": 576,
                    "start": 499,
                    "word": "kuogopa"
                  },
                  {
                    "end": 640,
                    "start": 577,
                    "word": "kidogo"
                  }
                ],
                "until": 640,
                "utterances": "Mwanzoni Simba alishangaa pia na kuogopa kidogo"
              }
            ],
            "sentence": "Mwanzoni, Simba alishangaa pia na kuogopa kidogo."
          }
        ],
        [
          {
            "narration": [
              {
                "audio": "lakini_mngurumo_mkubwa_ulisikika_kutoka_tumboni_mwake_kwani_alikuwa_na_njaa.mp3",
                "from": 34,
                "segmentation": [
                  {
                    "end": 104,
                    "start": 34,
                    "word": "Lakini"
                  },
                  {
                    "end": 221,
                    "start": 105,
                    "word": "mngurumo"
                  },
                  {
                    "end": 285,
                    "start": 222,
                    "word": "mkubwa"
                  },
                  {
                    "end": 413,
                    "start": 325,
                    "word": "ulisikika"
                  },
                  {
                    "end": 463,
                    "start": 414,
                    "word": "kutoka"
                  },
                  {
                    "end": 528,
                    "start": 464,
                    "word": "tumboni"
                  },
                  {
                    "end": 577,
                    "start": 529,
                    "word": "mwake"
                  },
                  {
                    "end": 653,
                    "start": 606,
                    "word": "kwani"
                  },
                  {
                    "end": 737,
                    "start": 659,
                    "word": "alikuwa"
                  },
                  {
                    "end": 762,
                    "start": 738,
                    "word": "na"
                  },
                  {
                    "end": 864,
                    "start": 763,
                    "word": "njaa"
                  }
                ],
                "until": 864,
                "utterances": "Lakini mngurumo mkubwa ulisikika kutoka tumboni mwake kwani alikuwa na njaa"
              }
            ],
            "sentence": "Lakini mngurumo mkubwa ulisikika kutoka tumboni mwake kwani alikuwa na njaa."
          }
        ]
      ]
    },
    {
      "image": "level2_14_page_06_image_0001.jpg",
      "text": [
        [
          {
            "narration": [
              {
                "audio": "mtu_yule_alijikuta_juu_ya_mti_mrefu.mp3",
                "from": 21,
                "segmentation": [
                  {
                    "end": 64,
                    "start": 21,
                    "word": "Mtu"
                  },
                  {
                    "end": 118,
                    "start": 65,
                    "word": "yule"
                  },
                  {
                    "end": 231,
                    "start": 119,
                    "word": "alijikuta"
                  },
                  {
                    "end": 279,
                    "start": 232,
                    "word": "juu"
                  },
                  {
                    "end": 293,
                    "start": 280,
                    "word": "ya"
                  },
                  {
                    "end": 347,
                    "start": 294,
                    "word": "mti"
                  },
                  {
                    "end": 400,
                    "start": 348,
                    "word": "mrefu"
                  }
                ],
                "until": 400,
                "utterances": "Mtu yule alijikuta juu ya mti mrefu"
              }
            ],
            "sentence": "Mtu yule alijikuta juu ya mti mrefu."
          }
        ],
        [
          {
            "narration": [
              {
                "audio": "alianza_kupiga_mayowe.mp3",
                "from": 23,
                "segmentation": [
                  {
                    "end": 99,
                    "start": 23,
                    "word": "Alianza"
                  },
                  {
                    "end": 182,
                    "start": 100,
                    "word": "kupiga"
                  },
                  {
                    "end": 254,
                    "start": 183,
                    "word": "mayowe"
                  }
                ],
                "until": 254,
                "utterances": "Alianza kupiga mayowe"
              }
            ],
            "sentence": "Alianza kupiga mayowe."
          }
        ]
      ]
    },
    {
      "image": "level2_14_page_07_image_0001.jpg",
      "text": [
        [
          {
            "narration": [
              {
                "audio": "simba_alilala_chini_ya_mti_akisubiri_mlo.mp3",
                "from": 2,
                "segmentation": [
                  {
                    "end": 74,
                    "start": 2,
                    "word": "Simba"
                  },
                  {
                    "end": 167,
                    "start": 87,
                    "word": "alilala"
                  },
                  {
                    "end": 225,
                    "start": 168,
                    "word": "chini"
                  },
                  {
                    "end": 233,
                    "start": 226,
                    "word": "ya"
                  },
                  {
                    "end": 283,
                    "start": 234,
                    "word": "mti"
                  },
                  {
                    "end": 393,
                    "start": 293,
                    "word": "akisubiri"
                  },
                  {
                    "end": 447,
                    "start": 394,
                    "word": "mlo"
                  }
                ],
                "until": 447,
                "utterances": "Simba alilala chini ya mti akisubiri mlo"
              }
            ],
            "sentence": "Simba alilala chini ya mti akisubiri mlo."
          }
        ],
        [
          {
            "narration": [
              {
                "audio": "muda_ulipozidi_kwenda_simba_alijifanya_kulala_usingizi.mp3",
                "from": 20,
                "segmentation": [
                  {
                    "end": 65,
                    "start": 20,
                    "word": "Muda"
                  },
                  {
                    "end": 166,
                    "start": 78,
                    "word": "ulipozidi"
                  },
                  {
                    "end": 228,
                    "start": 167,
                    "word": "kwenda"
                  },
                  {
                    "end": 319,
                    "start": 271,
                    "word": "Simba"
                  },
                  {
                    "end": 444,
                    "start": 320,
                    "word": "alijifanya"
                  },
                  {
                    "end": 516,
                    "start": 445,
                    "word": "kulala"
                  },
                  {
                    "end": 642,
                    "start": 517,
                    "word": "usingizi"
                  }
                ],
                "until": 642,
                "utterances": "Muda ulipozidi kwenda Simba alijifanya kulala usingizi"
              }
            ],
            "sentence": "Muda ulipozidi kwenda, Simba alijifanya kulala usingizi ."
          }
        ]
      ]
    },
    {
      "image": "level2_14_page_08_image_0001.jpg",
      "text": [
        [
          {
            "narration": [
              {
                "audio": "muda_mfupi_baadaye_mtu_yule_alilala_usingizi.mp3",
                "from": 20,
                "segmentation": [
                  {
                    "end": 70,
                    "start": 20,
                    "word": "Muda"
                  },
                  {
                    "end": 124,
                    "start": 71,
                    "word": "mfupi"
                  },
                  {
                    "end": 193,
                    "start": 125,
                    "word": "baadaye"
                  },
                  {
                    "end": 297,
                    "start": 263,
                    "word": "mtu"
                  },
                  {
                    "end": 344,
                    "start": 298,
                    "word": "yule"
                  },
                  {
                    "end": 455,
                    "start": 358,
                    "word": "alilala"
                  },
                  {
                    "end": 577,
                    "start": 456,
                    "word": "usingizi"
                  }
                ],
                "until": 577,
                "utterances": "Muda mfupi baadaye mtu yule alilala usingizi"
              }
            ],
            "sentence": "Muda mfupi baadaye, mtu yule alilala usingizi."
          }
        ],
        [
          {
            "narration": [
              {
                "audio": "kisha_akaamka_tena.mp3",
                "from": 2,
                "segmentation": [
                  {
                    "end": 75,
                    "start": 2,
                    "word": "Kisha"
                  },
                  {
                    "end": 167,
                    "start": 81,
                    "word": "akaamka"
                  },
                  {
                    "end": 212,
                    "start": 168,
                    "word": "tena"
                  }
                ],
                "until": 212,
                "utterances": "Kisha akaamka tena"
              }
            ],
            "sentence": "Kisha akaamka tena."
          }
        ],
        [
          {
            "narration": [
              {
                "audio": "mwishoni_alisinzia_na_kulala_fofofo.mp3",
                "from": 21,
                "segmentation": [
                  {
                    "end": 111,
                    "start": 21,
                    "word": "Mwishoni"
                  },
                  {
                    "end": 270,
                    "start": 151,
                    "word": "alisinzia"
                  },
                  {
                    "end": 294,
                    "start": 271,
                    "word": "na"
                  },
                  {
                    "end": 381,
                    "start": 295,
                    "word": "kulala"
                  },
                  {
                    "end": 520,
                    "start": 382,
                    "word": "fofofo"
                  }
                ],
                "until": 520,
                "utterances": "Mwishoni alisinzia na kulala fofofo"
              }
            ],
            "sentence": "Mwishoni alisinzia na kulala fofofo."
          }
        ]
      ]
    },
    {
      "image": "level2_14_page_09_image_0001.jpg",
      "text": [
        [
          {
            "narration": [
              {
                "audio": "lakini_mara_aliporomoka_kutoka_juu_na_kumwangukia_yule_simba_aliyelala.mp3",
                "from": 26,
                "segmentation": [
                  {
                    "end": 90,
                    "start": 26,
                    "word": "Lakini"
                  },
                  {
                    "end": 136,
                    "start": 91,
                    "word": "mara"
                  },
                  {
                    "end": 286,
                    "start": 155,
                    "word": "aliporomoka"
                  },
                  {
                    "end": 337,
                    "start": 287,
                    "word": "kutoka"
                  },
                  {
                    "end": 376,
                    "start": 338,
                    "word": "juu"
                  },
                  {
                    "end": 434,
                    "start": 417,
                    "word": "na"
                  },
                  {
                    "end": 556,
                    "start": 435,
                    "word": "kumwangukia"
                  },
                  {
                    "end": 596,
                    "start": 557,
                    "word": "yule"
                  },
                  {
                    "end": 642,
                    "start": 597,
                    "word": "Simba"
                  },
                  {
                    "end": 738,
                    "start": 643,
                    "word": "aliyelala"
                  }
                ],
                "until": 738,
                "utterances": "Lakini mara aliporomoka kutoka juu na kumwangukia yule Simba aliyelala"
              }
            ],
            "sentence": "Lakini mara aliporomoka kutoka juu na kumwangukia yule Simba aliyelala."
          }
        ]
      ]
    },
    {
      "image": "level2_14_page_10_image_0001.jpg",
      "text": [
        [
          {
            "narration": [
              {
                "audio": "wote_waliamka_wakiwa_wamechanganyikiwa_na_kuogopa.mp3",
                "from": 20,
                "segmentation": [
                  {
                    "end": 89,
                    "start": 20,
                    "word": "Wote"
                  },
                  {
                    "end": 183,
                    "start": 90,
                    "word": "waliamka"
                  },
                  {
                    "end": 237,
                    "start": 184,
                    "word": "wakiwa"
                  },
                  {
                    "end": 361,
                    "start": 238,
                    "word": "wamechanganyikiwa"
                  },
                  {
                    "end": 414,
                    "start": 398,
                    "word": "na"
                  },
                  {
                    "end": 502,
                    "start": 415,
                    "word": "kuogopa"
                  }
                ],
                "until": 502,
                "utterances": "Wote waliamka wakiwa wamechanganyikiwa na kuogopa"
              }
            ],
            "sentence": "Wote waliamka wakiwa wamechanganyikiwa na kuogopa."
          }
        ],
        [
          {
            "narration": [
              {
                "audio": "simba_alisahau_mlo_wake_na_kukimbilia_usalama_wake.mp3",
                "from": 21,
                "segmentation": [
                  {
                    "end": 83,
                    "start": 21,
                    "word": "Simba"
                  },
                  {
                    "end": 181,
                    "start": 97,
                    "word": "alisahau"
                  },
                  {
                    "end": 225,
                    "start": 182,
                    "word": "mlo"
                  },
                  {
                    "end": 276,
                    "start": 226,
                    "word": "wake"
                  },
                  {
                    "end": 337,
                    "start": 318,
                    "word": "na"
                  },
                  {
                    "end": 502,
                    "start": 338,
                    "word": "kukimbilia"
                  },
                  {
                    "end": 605,
                    "start": 541,
                    "word": "usalama"
                  },
                  {
                    "end": 647,
                    "start": 606,
                    "word": "wake"
                  }
                ],
                "until": 647,
                "utterances": "Simba alisahau mlo wake na kukimbilia usalama wake"
              }
            ],
            "sentence": "Simba alisahau mlo wake na kukimbilia usalama wake."
          }
        ]
      ]
    },
    {
      "image": "level2_14_page_11_image_0001.jpg",
      "text": [
        [
          {
            "narration": [
              {
                "audio": "mtu_yule_alianza_kukimbia_akielekea_upande_mmoja_na_simba.mp3",
                "from": 11,
                "segmentation": [
                  {
                    "end": 47,
                    "start": 11,
                    "word": "Mtu"
                  },
                  {
                    "end": 107,
                    "start": 48,
                    "word": "yule"
                  },
                  {
                    "end": 215,
                    "start": 147,
                    "word": "alianza"
                  },
                  {
                    "end": 310,
                    "start": 216,
                    "word": "kukimbia"
                  },
                  {
                    "end": 408,
                    "start": 311,
                    "word": "akielekea"
                  },
                  {
                    "end": 461,
                    "start": 409,
                    "word": "upande"
                  },
                  {
                    "end": 512,
                    "start": 462,
                    "word": "mmoja"
                  },
                  {
                    "end": 528,
                    "start": 513,
                    "word": "na"
                  },
                  {
                    "end": 582,
                    "start": 529,
                    "word": "Simba"
                  }
                ],
                "until": 582,
                "utterances": "Mtu yule alianza kukimbia akielekea upande mmoja na Simba"
              }
            ],
            "sentence": "Mtu yule alianza kukimbia akielekea upande mmoja na Simba."
          }
        ],
        [
          {
            "narration": [
              {
                "audio": "aligundua_kwamba_alikuwa_akikimbia_na_simba.mp3",
                "from": 21,
                "segmentation": [
                  {
                    "end": 117,
                    "start": 21,
                    "word": "Aligundua"
                  },
                  {
                    "end": 167,
                    "start": 118,
                    "word": "kwamba"
                  },
                  {
                    "end": 244,
                    "start": 168,
                    "word": "alikuwa"
                  },
                  {
                    "end": 331,
                    "start": 245,
                    "word": "akikimbia"
                  },
                  {
                    "end": 348,
                    "start": 332,
                    "word": "na"
                  },
                  {
                    "end": 398,
                    "start": 349,
                    "word": "Simba"
                  }
                ],
                "until": 398,
                "utterances": "Aligundua kwamba alikuwa akikimbia na Simba"
              }
            ],
            "sentence": "Aligundua kwamba alikuwa akikimbia na Simba!"
          }
        ]
      ]
    },
    {
      "image": "level2_14_page_12_image_0001.jpg",
      "text": [
        [
          {
            "narration": [
              {
                "audio": "kwa_hivyo_alibadilisha_mwelekeo_wake_na_kuepuka_kuliwa_na_simba.mp3",
                "from": 2,
                "segmentation": [
                  {
                    "end": 32,
                    "start": 2,
                    "word": "Kwa"
                  },
                  {
                    "end": 81,
                    "start": 33,
                    "word": "hivyo"
                  },
                  {
                    "end": 187,
                    "start": 82,
                    "word": "alibadilisha"
                  },
                  {
                    "end": 248,
                    "start": 188,
                    "word": "mwelekeo"
                  },
                  {
                    "end": 309,
                    "start": 249,
                    "word": "wake"
                  },
                  {
                    "end": 357,
                    "start": 345,
                    "word": "na"
                  },
                  {
                    "end": 451,
                    "start": 358,
                    "word": "kuepuka"
                  },
                  {
                    "end": 500,
                    "start": 452,
                    "word": "kuliwa"
                  },
                  {
                    "end": 516,
                    "start": 501,
                    "word": "na"
                  },
                  {
                    "end": 563,
                    "start": 517,
                    "word": "Simba"
                  }
                ],
                "until": 563,
                "utterances": "Kwa hivyo alibadilisha mwelekeo wake na kuepuka kuliwa na Simba"
              }
            ],
            "sentence": "Kwa hivyo alibadilisha mwelekeo wake na kuepuka kuliwa na Simba!"
          }
        ]
      ]
    }
  ],
  "illustrators": "Helder de Paz Alexandre",
  "language": "Kiswahili",
  "level": "2",
  "license": "CC-BY Version 3.0 Unported Licence",
  "status": "Translated by: Brigid Simiyu",
  "title": "Mtu na Simba",
  "titleimage": "level2_14_page_01_image_0001.jpg"
}