{
  "authors": "RoboTutor",
  "copyright": "",
  "data": [
    {
      "image": "92_txt.png",
      "text": [
        [
          {
            "narration": [
              {
                "audio": "tisini.mp3",
                "from": 22,
                "segmentation": [
                  {
                    "end": 111,
                    "start": 22,
                    "word": "tisini"
                  }
                ],
                "until": 155,
                "utterances": "tisini"
              },
              {
                "audio": "na.mp3",
                "from": 175,
                "segmentation": [
                  {
                    "end": 57,
                    "start": 20,
                    "word": "na"
                  }
                ],
                "until": 251,
                "utterances": "na"
              },
              {
                "audio": "mbili.mp3",
                "from": 273,
                "segmentation": [
                  {
                    "end": 90,
                    "start": 22,
                    "word": "mbili"
                  }
                ],
                "until": 392,
                "utterances": "mbili"
              }
            ],
            "sentence": "tisini na mbili"
          }
        ]
      ]
    },
    {
      "image": "91_txt.png",
      "text": [
        [
          {
            "narration": [
              {
                "audio": "tisini.mp3",
                "from": 22,
                "segmentation": [
                  {
                    "end": 111,
                    "start": 22,
                    "word": "tisini"
                  }
                ],
                "until": 155,
                "utterances": "tisini"
              },
              {
                "audio": "na.mp3",
                "from": 175,
                "segmentation": [
                  {
                    "end": 57,
                    "start": 20,
                    "word": "na"
                  }
                ],
                "until": 251,
                "utterances": "na"
              },
              {
                "audio": "moja.mp3",
                "from": 272,
                "segmentation": [
                  {
                    "end": 75,
                    "start": 21,
                    "word": "moja"
                  }
                ],
                "until": 376,
                "utterances": "moja"
              }
            ],
            "sentence": "tisini na moja"
          }
        ]
      ]
    },
    {
      "image": "90_txt.png",
      "text": [
        [
          {
            "narration": [
              {
                "audio": "tisini.mp3",
                "from": 22,
                "segmentation": [
                  {
                    "end": 111,
                    "start": 22,
                    "word": "tisini"
                  }
                ],
                "until": 155,
                "utterances": "tisini"
              }
            ],
            "sentence": "tisini"
          }
        ]
      ]
    },
    {
      "image": "89_txt.png",
      "text": [
        [
          {
            "narration": [
              {
                "audio": "themanini.mp3",
                "from": 2,
                "segmentation": [
                  {
                    "end": 122,
                    "start": 2,
                    "word": "themanini"
                  }
                ],
                "until": 173,
                "utterances": "themanini"
              },
              {
                "audio": "na.mp3",
                "from": 193,
                "segmentation": [
                  {
                    "end": 57,
                    "start": 20,
                    "word": "na"
                  }
                ],
                "until": 269,
                "utterances": "na"
              },
              {
                "audio": "tisa.mp3",
                "from": 291,
                "segmentation": [
                  {
                    "end": 73,
                    "start": 22,
                    "word": "tisa"
                  }
                ],
                "until": 387,
                "utterances": "tisa"
              }
            ],
            "sentence": "themanini na tisa"
          }
        ]
      ]
    },
    {
      "image": "88_txt.png",
      "text": [
        [
          {
            "narration": [
              {
                "audio": "themanini.mp3",
                "from": 2,
                "segmentation": [
                  {
                    "end": 122,
                    "start": 2,
                    "word": "themanini"
                  }
                ],
                "until": 173,
                "utterances": "themanini"
              },
              {
                "audio": "na.mp3",
                "from": 193,
                "segmentation": [
                  {
                    "end": 57,
                    "start": 20,
                    "word": "na"
                  }
                ],
                "until": 269,
                "utterances": "na"
              },
              {
                "audio": "nane.mp3",
                "from": 290,
                "segmentation": [
                  {
                    "end": 81,
                    "start": 21,
                    "word": "nane"
                  }
                ],
                "until": 400,
                "utterances": "nane"
              }
            ],
            "sentence": "themanini na nane"
          }
        ]
      ]
    },
    {
      "image": "87_txt.png",
      "text": [
        [
          {
            "narration": [
              {
                "audio": "themanini.mp3",
                "from": 2,
                "segmentation": [
                  {
                    "end": 122,
                    "start": 2,
                    "word": "themanini"
                  }
                ],
                "until": 173,
                "utterances": "themanini"
              },
              {
                "audio": "na.mp3",
                "from": 193,
                "segmentation": [
                  {
                    "end": 57,
                    "start": 20,
                    "word": "na"
                  }
                ],
                "until": 269,
                "utterances": "na"
              },
              {
                "audio": "saba.mp3",
                "from": 289,
                "segmentation": [
                  {
                    "end": 81,
                    "start": 20,
                    "word": "saba"
                  }
                ],
                "until": 407,
                "utterances": "saba"
              }
            ],
            "sentence": "themanini na saba"
          }
        ]
      ]
    },
    {
      "image": "86_txt.png",
      "text": [
        [
          {
            "narration": [
              {
                "audio": "themanini.mp3",
                "from": 2,
                "segmentation": [
                  {
                    "end": 122,
                    "start": 2,
                    "word": "themanini"
                  }
                ],
                "until": 173,
                "utterances": "themanini"
              },
              {
                "audio": "na.mp3",
                "from": 193,
                "segmentation": [
                  {
                    "end": 57,
                    "start": 20,
                    "word": "na"
                  }
                ],
                "until": 269,
                "utterances": "na"
              },
              {
                "audio": "sita.mp3",
                "from": 290,
                "segmentation": [
                  {
                    "end": 88,
                    "start": 21,
                    "word": "sita"
                  }
                ],
                "until": 407,
                "utterances": "sita"
              }
            ],
            "sentence": "themanini na sita"
          }
        ]
      ]
    },
    {
      "image": "85_txt.png",
      "text": [
        [
          {
            "narration": [
              {
                "audio": "themanini.mp3",
                "from": 2,
                "segmentation": [
                  {
                    "end": 122,
                    "start": 2,
                    "word": "themanini"
                  }
                ],
                "until": 173,
                "utterances": "themanini"
              },
              {
                "audio": "na.mp3",
                "from": 193,
                "segmentation": [
                  {
                    "end": 57,
                    "start": 20,
                    "word": "na"
                  }
                ],
                "until": 269,
                "utterances": "na"
              },
              {
                "audio": "tano.mp3",
                "from": 290,
                "segmentation": [
                  {
                    "end": 78,
                    "start": 21,
                    "word": "tano"
                  }
                ],
                "until": 399,
                "utterances": "tano"
              }
            ],
            "sentence": "themanini na tano"
          }
        ]
      ]
    },
    {
      "image": "84_txt.png",
      "text": [
        [
          {
            "narration": [
              {
                "audio": "themanini.mp3",
                "from": 2,
                "segmentation": [
                  {
                    "end": 122,
                    "start": 2,
                    "word": "themanini"
                  }
                ],
                "until": 173,
                "utterances": "themanini"
              },
              {
                "audio": "na.mp3",
                "from": 193,
                "segmentation": [
                  {
                    "end": 57,
                    "start": 20,
                    "word": "na"
                  }
                ],
                "until": 269,
                "utterances": "na"
              },
              {
                "audio": "nne.mp3",
                "from": 290,
                "segmentation": [
                  {
                    "end": 70,
                    "start": 21,
                    "word": "nne"
                  }
                ],
                "until": 381,
                "utterances": "nne"
              }
            ],
            "sentence": "themanini na nne"
          }
        ]
      ]
    },
    {
      "image": "83_txt.png",
      "text": [
        [
          {
            "narration": [
              {
                "audio": "themanini.mp3",
                "from": 2,
                "segmentation": [
                  {
                    "end": 122,
                    "start": 2,
                    "word": "themanini"
                  }
                ],
                "until": 173,
                "utterances": "themanini"
              },
              {
                "audio": "na.mp3",
                "from": 193,
                "segmentation": [
                  {
                    "end": 57,
                    "start": 20,
                    "word": "na"
                  }
                ],
                "until": 269,
                "utterances": "na"
              },
              {
                "audio": "tatu.mp3",
                "from": 290,
                "segmentation": [
                  {
                    "end": 75,
                    "start": 21,
                    "word": "tatu"
                  }
                ],
                "until": 387,
                "utterances": "tatu"
              }
            ],
            "sentence": "themanini na tatu"
          }
        ]
      ]
    }
  ],
  "illustrators": "",
  "language": "Kiswahili",
  "level": "",
  "license": "",
  "status": "",
  "title": "numstory.0..100.DD_OFF1_DES_RAND.level21"
}